design.sv
`timescale 1ns/1ps

module fir_filter (
    input clk,
    input reset,
    input [7:0] x_in,
    output reg [15:0] y_out
);

    reg [7:0] x_reg0, x_reg1, x_reg2;
    parameter h0 = 1, h1 = 2, h2 = 1;

    always @(posedge clk or posedge reset) begin
        if (reset) begin
            x_reg0 <= 0; x_reg1 <= 0; x_reg2 <= 0;
            y_out <= 0;
        end else begin
            x_reg2 <= x_reg1;
            x_reg1 <= x_reg0;
            x_reg0 <= x_in;

            y_out <= h0*x_reg0 + h1*x_reg1 + h2*x_reg2;
        end
    end

endmodule

testbench.sv

`timescale 1ns/1ps

module tb_fir_filter;

    reg clk;
    reg reset;
    reg [7:0] x_in;
    wire [15:0] y_out;

    fir_filter uut (
        .clk(clk),
        .reset(reset),
        .x_in(x_in),
        .y_out(y_out)
    );

    always #5 clk = ~clk;

    initial begin
        $dumpfile("fir.vcd");
        $dumpvars(0, tb_fir_filter);

        clk = 0;
        reset = 1; x_in = 0;
        #10 reset = 0;

        // Apply input sequence
        #10 x_in = 8'd10;
        #10 x_in = 8'd20;
        #10 x_in = 8'd30;
        #10 x_in = 8'd0;
        #10 x_in = 8'd5;

        #50 $finish;
    end

endmodule

fir.vcd
$date
	Fri Jun 20 02:35:04 2025
$end
$version
	Icarus Verilog
$end
$timescale
	1ps
$end
$scope module tb_fir_filter $end
$var wire 16 ! y_out [15:0] $end
$var reg 1 " clk $end
$var reg 1 # reset $end
$var reg 8 $ x_in [7:0] $end
$scope module uut $end
$var wire 1 " clk $end
$var wire 1 # reset $end
$var wire 8 % x_in [7:0] $end
$var parameter 32 & h0 $end
$var parameter 32 ' h1 $end
$var parameter 32 ( h2 $end
$var reg 8 ) x_reg0 [7:0] $end
$var reg 8 * x_reg1 [7:0] $end
$var reg 8 + x_reg2 [7:0] $end
$var reg 16 , y_out [15:0] $end
$upscope $end
$upscope $end
$enddefinitions $end
$comment Show the parameter values. $end
$dumpall
b1 (
b10 '
b1 &
$end
#0
$dumpvars
b0 ,
b0 +
b0 *
b0 )
b0 %
b0 $
1#
0"
b0 !
$end
#5000
1"
#10000
0"
0#
#15000
1"
#20000
0"
b1010 $
b1010 %
#25000
b1010 )
1"
#30000
0"
b10100 $
b10100 %
#35000
b1010 !
b1010 ,
b10100 )
b1010 *
1"
#40000
0"
b11110 $
b11110 %
#45000
b101000 !
b101000 ,
b11110 )
b10100 *
b1010 +
1"
#50000
0"
b0 $
b0 %
#55000
b1010000 !
b1010000 ,
b0 )
b11110 *
b10100 +
1"
#60000
0"
b101 $
b101 %
#65000
b101 )
b0 *
b11110 +
1"
#70000
0"
#75000
b100011 !
b100011 ,
b101 *
b0 +
1"
#80000
0"
#85000
b1111 !
b1111 ,
b101 +
1"
#90000
0"
#95000
b10100 !
b10100 ,
1"
